dynexus/__init__.py
dynexus-0.0.0.dist-info/METADATA
dynexus-0.0.0.dist-info/WHEEL
dynexus-0.0.0.dist-info/top_level.txt
dynexus-0.0.0.dist-info/RECORD
